{"assets/images/breakfast.png":["assets/images/breakfast.png"],"assets/images/chair.png":["assets/images/chair.png"],"assets/images/close.png":["assets/images/close.png"],"assets/images/colddrinks.png":["assets/images/colddrinks.png"],"assets/images/dessert.png":["assets/images/dessert.png"],"assets/images/dinner.png":["assets/images/dinner.png"],"assets/images/floor.png":["assets/images/floor.png"],"assets/images/hitea.png":["assets/images/hitea.png"],"assets/images/leaf.png":["assets/images/leaf.png"],"assets/images/lunch.png":["assets/images/lunch.png"],"assets/images/p1.png":["assets/images/p1.png"],"assets/images/p2.png":["assets/images/p2.png"],"assets/images/p3.png":["assets/images/p3.png"],"assets/images/p4.png":["assets/images/p4.png"],"assets/images/p5.png":["assets/images/p5.png"],"assets/images/p6.png":["assets/images/p6.png"],"assets/images/p7.png":["assets/images/p7.png"],"assets/images/p8.png":["assets/images/p8.png"],"assets/images/p9.png":["assets/images/p9.png"],"assets/images/table.png":["assets/images/table.png"],"assets/images/tiles.png":["assets/images/tiles.png"],"assets/jsons/sales.json":["assets/jsons/sales.json"],"assets/svgs/avatar.png":["assets/svgs/avatar.png"],"assets/svgs/easypaisa.svg":["assets/svgs/easypaisa.svg"],"assets/svgs/jazzcash.svg":["assets/svgs/jazzcash.svg"],"assets/svgs/mastercard.svg":["assets/svgs/mastercard.svg"],"assets/svgs/paypal.svg":["assets/svgs/paypal.svg"],"assets/svgs/poslogo.png":["assets/svgs/poslogo.png"],"assets/svgs/pro1.png":["assets/svgs/pro1.png"],"assets/svgs/productImg.png":["assets/svgs/productImg.png"],"assets/svgs/signin.svg":["assets/svgs/signin.svg"],"assets/svgs/stripe.svg":["assets/svgs/stripe.svg"],"assets/svgs/visa.svg":["assets/svgs/visa.svg"],"packages/cupertino_icons/assets/CupertinoIcons.ttf":["packages/cupertino_icons/assets/CupertinoIcons.ttf"],"packages/dash_chat_2/assets/placeholder.png":["packages/dash_chat_2/assets/placeholder.png"],"packages/dash_chat_2/assets/profile_placeholder.png":["packages/dash_chat_2/assets/profile_placeholder.png"],"packages/font_awesome_flutter/lib/fonts/fa-brands-400.ttf":["packages/font_awesome_flutter/lib/fonts/fa-brands-400.ttf"],"packages/font_awesome_flutter/lib/fonts/fa-regular-400.ttf":["packages/font_awesome_flutter/lib/fonts/fa-regular-400.ttf"],"packages/font_awesome_flutter/lib/fonts/fa-solid-900.ttf":["packages/font_awesome_flutter/lib/fonts/fa-solid-900.ttf"]}